README.rst
setup.py
flask_sqlalchemy_rls/__init__.py
flask_sqlalchemy_rls.egg-info/PKG-INFO
flask_sqlalchemy_rls.egg-info/SOURCES.txt
flask_sqlalchemy_rls.egg-info/dependency_links.txt
flask_sqlalchemy_rls.egg-info/requires.txt
flask_sqlalchemy_rls.egg-info/top_level.txt